ivmodels/__init__.py
ivmodels/confidence_set.py
ivmodels/quadric.py
ivmodels/simulate.py
ivmodels/summary.py
ivmodels/utils.py
ivmodels/models/__init__.py
ivmodels/models/anchor_regression.py
ivmodels/models/kclass.py
ivmodels/models/pulse.py
ivmodels/models/space_iv.py
ivmodels/tests/__init__.py
ivmodels/tests/anderson_rubin.py
ivmodels/tests/conditional_likelihood_ratio.py
ivmodels/tests/j.py
ivmodels/tests/lagrange_multiplier.py
ivmodels/tests/likelihood_ratio.py
ivmodels/tests/pulse.py
ivmodels/tests/rank.py
ivmodels/tests/residual_prediction.py
ivmodels/tests/wald.py
ivmodels-0.9.0.dist-info/licenses/LICENSE
ivmodels-0.9.0.dist-info/METADATA
ivmodels-0.9.0.dist-info/WHEEL
ivmodels-0.9.0.dist-info/top_level.txt
ivmodels-0.9.0.dist-info/RECORD
