Metadata-Version: 2.4
Name: ivmodels
Version: 0.9.0
Summary: IV Models
Author-email: Malte Londschien <malte@londschien.ch>
Project-URL: homepage, https://github.com/mlondschien/ivmodels/
Classifier: License :: OSI Approved :: BSD License
Classifier: Programming Language :: Python
Requires-Python: >=3.7
License-File: LICENSE
Requires-Dist: numpy
Requires-Dist: scikit-learn
Requires-Dist: glum
Requires-Dist: scipy
Requires-Dist: numba
Dynamic: license-file
